kiteworks_io/__init__.py
kiteworks_io/kiteworks_io.py
kiteworks_io-0.1.5.dist-info/METADATA
kiteworks_io-0.1.5.dist-info/WHEEL
kiteworks_io-0.1.5.dist-info/RECORD
