Metadata-Version: 2.4
Name: kiteworks-io
Version: 0.1.5
Summary: 
Author: Abdel.ALIAOUI
Author-email: abdel.aliaoui@oecd.org
Requires-Python: >=3.12,<4.0
Classifier: Programming Language :: Python :: 3
Classifier: Programming Language :: Python :: 3.12
Classifier: Programming Language :: Python :: 3.13
Classifier: Programming Language :: Python :: 3.14
Requires-Dist: pandas (>=2.2.3,<3.0.0)
Requires-Dist: paramiko (>=3.5.1,<4.0.0)
Requires-Dist: pysocks (>=1.7.1,<2.0.0)
